{
    "total": [
        {
            "id": "61550781316064",
            "count": 393
        },
        {
            "id": "100011152309303",
            "count": 38
        },
        {
            "id": "100071935771315",
            "count": 7
        }
    ],
    "week": [
        {
            "id": "61550781316064",
            "count": 393
        },
        {
            "id": "100011152309303",
            "count": 38
        },
        {
            "id": "100071935771315",
            "count": 7
        }
    ],
    "day": [
        {
            "id": "61550781316064",
            "count": 393
        },
        {
            "id": "100011152309303",
            "count": 38
        },
        {
            "id": "100071935771315",
            "count": 7
        }
    ],
    "time": 0
}